<?xml version="1.0" ?>
<?xml-stylesheet type='text/xsl' href='interface.xsl'?>
<interface uri="http://ryppl.github.com/feeds/boost/Lambda-dbg.xml" xmlns="http://zero-install.sourceforge.net/2004/injector/interface" xmlns:compile="http://zero-install.sourceforge.net/2006/namespaces/0compile" xmlns:dc="http://purl.org/dc/elements/1.1/">
  <name>BoostLambda</name>
  <icon href="http://svn.boost.org/svn/boost/website/public_html/live/gfx/boost-dark-trans.png" type="image/png"/>
  <summary>A C++ library from Boost.org</summary>
  <homepage>http://www.boost.org/libs/lambda/</homepage>
  <dc:author>Gary Powell</dc:author>
  <dc:author>Jaakko Järvi</dc:author>
  <description>Define small unnamed function objects at the
    actual call site, and more.</description>
  <category type="http://boost.org/lib-categories">Function-objects</category>
  <group license="OSI Approved :: Boost Software License 1.0 (BSL-1.0)">
    <implementation arch="*-src" id="78f1922e-47f3-4978-8315-062a4abca730" released="2012-04-28" stability="testing" version="1.49-post-201204281951">
      <archive extract="boost-lib-lambda-9140145" href="http://nodeload.github.com/boost-lib/lambda/zipball/914014514c7cdee429f9c095174533abc69b4934" size="166956" type="application/zip"/>
      <manifest-digest sha256="b40c0cc392beb10c7f1937e2d2a03cc06d9f601e4bff69c05d819730a4771b99"/>
    </implementation>
    <command name="compile">
      <runner interface="http://ryppl.github.com/feeds/ryppl/0cmake.xml">
        <version not-before="0.8-pre-201204281522"/>
        <arg>--component=dbg</arg>
        <arg>--overlay=${BOOST_CMAKELISTS_OVERLAY}</arg>
      </runner>
      <requires interface="http://ryppl.github.com/feeds/boost/CMakeLists.xml">
        <environment insert="lambda" mode="replace" name="BOOST_CMAKELISTS_OVERLAY"/>
      </requires>
    </command>
  </group>
</interface>
<!-- Base64 Signature
iEYEABECAAYFAk+cSj8ACgkQxnV5mk56UjEoFACbBPtZ3Lnkv5YogHV0K+F/+c75siEAoIJPgdDG
3bmtucnThKvVRnZruza0

-->
