<?xml version="1.0" ?>
<?xml-stylesheet type='text/xsl' href='interface.xsl'?>
<interface uri="http://ryppl.github.com/feeds/boost/optional-src.xml" xmlns="http://zero-install.sourceforge.net/2004/injector/interface" xmlns:compile="http://zero-install.sourceforge.net/2006/namespaces/0compile" xmlns:dc="http://purl.org/dc/elements/1.1/">
  <name>Boost.Optional (source code)</name>
  <icon href="http://svn.boost.org/svn/boost/website/public_html/live/gfx/boost-dark-trans.png" type="image/png"/>
  <summary>A C++ library from Boost.org</summary>
  <homepage>http://www.boost.org/libs/optional/</homepage>
  <dc:author>Fernando Cacciola</dc:author>
  <description>Discriminated-union wrapper for optional
    values.</description>
  <category type="http://boost.org/lib-categories">Miscellaneous</category>
  <group license="OSI Approved :: Boost Software License 1.0 (BSL-1.0)">
    <implementation arch="*-*" id="b1b061c7-096d-43dd-88d5-1169fb401b4a" released="2012-05-03" stability="testing" version="1.49-post-201205030432">
      <archive extract="boost-lib-optional-b0f724d" href="http://nodeload.github.com/boost-lib/optional/zipball/b0f724d902d2101bfcbb2a83c6572b7fbc50f0c7" size="100931" type="application/zip"/>
      <manifest-digest sha1new="1a74efbcedb71ee0e5f38a4932140d3d4323d8af"/>
    </implementation>
  </group>
</interface>
<!-- Base64 Signature
iEYEABECAAYFAk+iCnUACgkQxnV5mk56UjF50gCfaN+T2QdDBwt6RdtE0ezu4kts5skAmwVx/Rah
0T85vCZbuFF7Ko8mUqGW

-->
