<?xml version="1.0" ?>
<?xml-stylesheet type='text/xsl' href='interface.xsl'?>
<interface uri="https://raw.github.com/ryppl/feeds/gh-pages/boost/pool-src.xml" xmlns="http://zero-install.sourceforge.net/2004/injector/interface" xmlns:compile="http://zero-install.sourceforge.net/2006/namespaces/0compile" xmlns:dc="http://purl.org/dc/elements/1.1/" xmlns:ryppl="http://ryppl.org/2012">
  <name>Boost.Pool (source code)</name>
  <icon href="http://svn.boost.org/svn/boost/website/public_html/live/gfx/boost-dark-trans.png" type="image/png"/>
  <ryppl:vcs-repository href="http://github.com/boost-lib/pool.git" type="git"/>
  <summary>A C++ library from Boost.org</summary>
  <homepage>http://www.boost.org/libs/pool/</homepage>
  <dc:author>Steve Cleary</dc:author>
  <description>Memory pool management.</description>
  <category type="http://boost.org/lib-categories/2012">Memory</category>
  <group license="OSI Approved :: Boost Software License 1.0 (BSL-1.0)">
    <implementation arch="*-*" id="4ac26f29-180d-4a63-94d7-ee6a5e46defb" released="2012-09-26" ryppl:vcs-revision="719c7a411a83de9022e15a61535fe13dd2084f7c" stability="developer" version="1.51-post-2012.09.26.1650">
      <archive extract="boost-lib-pool-719c7a4" href="http://nodeload.github.com/boost-lib/pool/zipball/719c7a411a83de9022e15a61535fe13dd2084f7c" size="1045060" type="application/zip"/>
      <manifest-digest sha1new="7d1352c8851171d272f8263743843a93ba3dba54"/>
    </implementation>
    <requires interface="https://raw.github.com/ryppl/feeds/gh-pages/boost/math-src.xml"/>
    <requires interface="https://raw.github.com/ryppl/feeds/gh-pages/boost/utility-src.xml"/>
    <requires interface="https://raw.github.com/ryppl/feeds/gh-pages/boost/core-src.xml"/>
    <requires interface="https://raw.github.com/ryppl/feeds/gh-pages/boost/exception-src.xml"/>
    <requires interface="https://raw.github.com/ryppl/feeds/gh-pages/boost/config-src.xml"/>
    <requires interface="https://raw.github.com/ryppl/feeds/gh-pages/boost/type_traits-src.xml"/>
    <command name="develop">
      <runner interface="https://raw.github.com/ryppl/feeds/gh-pages/ryppl/ryppl.xml"/>
    </command>
  </group>
</interface>
<!-- Base64 Signature
iEYEABECAAYFAlBjM98ACgkQxnV5mk56UjFbWgCgnwTUoCrQON0JoZaIo3pbnjBIP80Anjy3UrxF
oQX/8X9S2wpbB/+0kTvc

-->
