<?xml version="1.0" ?>
<?xml-stylesheet type='text/xsl' href='interface.xsl'?>
<interface uri="http://ryppl.github.com/feeds/boost/quickbook-src.xml" xmlns="http://zero-install.sourceforge.net/2004/injector/interface" xmlns:compile="http://zero-install.sourceforge.net/2006/namespaces/0compile" xmlns:dc="http://purl.org/dc/elements/1.1/">
  <name>Quickbook (source code)</name>
  <icon href="http://svn.boost.org/svn/boost/website/public_html/live/gfx/boost-dark-trans.png" type="image/png"/>
  <summary>A C++ library from Boost.org</summary>
  <homepage>http://www.boost.org/</homepage>
  <description>Regular expressions that can be written as strings
    or as expression templates, and which can refer to each other
    and themselves recursively with the power of context-free
    grammars.</description>
  <group license="OSI Approved :: Boost Software License 1.0 (BSL-1.0)">
    <implementation arch="*-*" id="6b077c4d-6989-4da5-985e-b3574c446562" released="2012-05-01" stability="testing" version="1.49-post-201205020336">
      <archive extract="boost-lib-quickbook-83b29d7" href="http://nodeload.github.com/boost-lib/quickbook/zipball/83b29d7724222628781e71a4b4b42cc9ac77d4ab" size="436928" type="application/zip"/>
      <manifest-digest sha1new="27846dd16a4f3f9180f23efc0bbc2798a9912713"/>
    </implementation>
  </group>
</interface>
<!-- Base64 Signature
iEYEABECAAYFAk+gq7cACgkQxnV5mk56UjF4MgCbBnvfSq3mLJuSM/Km/J0Hf525/rcAoJw8stU2
2xAWCP7vHsSwk9EPU9Gd

-->
