<?xml version="1.0" ?>
<?xml-stylesheet type='text/xsl' href='interface.xsl'?>
<interface uri="http://ryppl.github.com/feeds/boost/UUID-dbg.xml" xmlns="http://zero-install.sourceforge.net/2004/injector/interface" xmlns:compile="http://zero-install.sourceforge.net/2006/namespaces/0compile" xmlns:dc="http://purl.org/dc/elements/1.1/">
  <name>BoostUUID</name>
  <icon href="http://svn.boost.org/svn/boost/website/public_html/live/gfx/boost-dark-trans.png" type="image/png"/>
  <summary>A C++ library from Boost.org</summary>
  <homepage>http://www.boost.org/libs/uuid/</homepage>
  <dc:author>Andy Tompkins</dc:author>
  <description>A universally unique identifier.</description>
  <category type="http://boost.org/lib-categories">Domain</category>
  <category type="http://boost.org/lib-categories">Data</category>
  <group license="OSI Approved :: Boost Software License 1.0 (BSL-1.0)">
    <implementation arch="*-src" id="0b2365b1-a196-401d-820e-acb466f6c12a" released="2012-04-30" stability="testing" version="1.49-post-201204301337">
      <archive extract="boost-lib-uuid-9792b68" href="http://nodeload.github.com/boost-lib/uuid/zipball/9792b6844e27783e0aabf8c368202f4501c5edc0" size="48953" type="application/zip"/>
      <manifest-digest sha256="aea458dcfd6f6750615883d9271c554ad60c2da5f4c7b8aac4bc4b6d2116a284"/>
    </implementation>
    <command name="compile">
      <runner interface="http://ryppl.github.com/feeds/ryppl/0cmake.xml">
        <version not-before="0.8-pre-201204291303"/>
        <arg>--component=dbg</arg>
        <arg>--overlay=${BOOST_CMAKELISTS_OVERLAY}</arg>
      </runner>
      <requires interface="http://ryppl.github.com/feeds/boost/CMakeLists.xml">
        <environment insert="uuid" mode="replace" name="BOOST_CMAKELISTS_OVERLAY"/>
      </requires>
    </command>
  </group>
</interface>
<!-- Base64 Signature
iEYEABECAAYFAk+elbYACgkQxnV5mk56UjG8kQCgkoHW0wYeFgjfq4I9XZUY+8msmF0An1nCnQyv
khTfA7ByS4fox/mn34uJ

-->
