<?xml version="1.0" ?>
<?xml-stylesheet type='text/xsl' href='interface.xsl'?>
<interface uri="https://raw.github.com/ryppl/feeds/gh-pages/boost/variant-src.xml" xmlns="http://zero-install.sourceforge.net/2004/injector/interface" xmlns:compile="http://zero-install.sourceforge.net/2006/namespaces/0compile" xmlns:dc="http://purl.org/dc/elements/1.1/" xmlns:ryppl="http://ryppl.org/2012">
  <name>Boost.Variant (source code)</name>
  <icon href="http://svn.boost.org/svn/boost/website/public_html/live/gfx/boost-dark-trans.png" type="image/png"/>
  <ryppl:vcs-repository href="http://github.com/boost-lib/variant.git" type="git"/>
  <summary>A C++ library from Boost.org</summary>
  <homepage>http://www.boost.org/libs/variant/</homepage>
  <dc:author>Eric Friedman</dc:author>
  <dc:author>Itay Maman</dc:author>
  <description>Safe, generic, stack-based discriminated union
    container.</description>
  <category type="http://boost.org/lib-categories/2012">Data</category>
  <category type="http://boost.org/lib-categories/2012">Containers</category>
  <group license="OSI Approved :: Boost Software License 1.0 (BSL-1.0)">
    <implementation arch="*-*" id="c488a1ea-0b88-46f8-9fba-89f7ef19436d" released="2012-05-16" ryppl:vcs-revision="cd8c6fef77ce8bccba56dbac36f800cd47bbd889" stability="testing" version="1.49-post-2012.05.16.2056">
      <archive extract="boost-lib-variant-cd8c6fe" href="http://nodeload.github.com/boost-lib/variant/zipball/cd8c6fef77ce8bccba56dbac36f800cd47bbd889" size="106727" type="application/zip"/>
      <manifest-digest sha1new="b63a9b352ec3d2d89ccfe67094919526bbef9bfd"/>
    </implementation>
    <requires interface="https://raw.github.com/ryppl/feeds/gh-pages/boost/mpl-src.xml"/>
    <requires interface="https://raw.github.com/ryppl/feeds/gh-pages/boost/utility-src.xml"/>
    <requires interface="https://raw.github.com/ryppl/feeds/gh-pages/boost/core-src.xml"/>
    <requires interface="https://raw.github.com/ryppl/feeds/gh-pages/boost/functional-src.xml"/>
    <requires interface="https://raw.github.com/ryppl/feeds/gh-pages/boost/preprocessor-src.xml"/>
    <requires interface="https://raw.github.com/ryppl/feeds/gh-pages/boost/config-src.xml"/>
    <requires interface="https://raw.github.com/ryppl/feeds/gh-pages/boost/static_assert-src.xml"/>
    <requires interface="https://raw.github.com/ryppl/feeds/gh-pages/boost/type_traits-src.xml"/>
    <command name="develop">
      <runner interface="https://raw.github.com/ryppl/feeds/gh-pages/ryppl/ryppl.xml"/>
    </command>
  </group>
</interface>
<!-- Base64 Signature
iEYEABECAAYFAk+0FUQACgkQxnV5mk56UjF2LwCeMyPLhHInD0NhdJT2yRwApvncbq4AoKIKwRmf
H4c0DiLnH9ht+PHLFIq/

-->
